use/__init__.py
use-0.1.0.dist-info/METADATA
use-0.1.0.dist-info/RECORD
use-0.1.0.dist-info/WHEEL
use-0.1.0.dist-info/top_level.txt
