Metadata-Version: 2.1
Name: use
Version: 0.1.0
Summary: A Library For Dynamically Importing Modules. Inspired By **Node.js** `require` Function.
Home-page: https://github.com/ShardulNalegave/use.py
Author: Shardul Nalegave
Author-email: nalegaveshardul40@gmail.com
License: MIT
Platform: UNKNOWN
Classifier: Programming Language :: Python :: 3
Classifier: Programming Language :: Python :: Implementation :: CPython
Classifier: Intended Audience :: Developers
Classifier: License :: OSI Approved :: MIT License
Classifier: Natural Language :: English
Classifier: Operating System :: OS Independent
Classifier: Topic :: Utilities
